dg_cli/__init__.py
dg_cli/component.py
dg_cli/context.py
dg_cli/error.py
dg_cli/generate.py
dg_cli/py.typed
dg_cli/utils.py
dg_cli/version.py
dg_cli/cli/__init__.py
dg_cli/cli/generate.py
dg_cli/cli/list.py
dg_cli/templates/CODE_LOCATION_NAME_PLACEHOLDER/pyproject.toml.jinja
dg_cli/templates/CODE_LOCATION_NAME_PLACEHOLDER/CODE_LOCATION_NAME_PLACEHOLDER/__init__.py
dg_cli/templates/CODE_LOCATION_NAME_PLACEHOLDER/CODE_LOCATION_NAME_PLACEHOLDER/definitions.py
dg_cli/templates/CODE_LOCATION_NAME_PLACEHOLDER/CODE_LOCATION_NAME_PLACEHOLDER/components/.gitkeep
dg_cli/templates/CODE_LOCATION_NAME_PLACEHOLDER/CODE_LOCATION_NAME_PLACEHOLDER/lib/__init__.py
dg_cli/templates/CODE_LOCATION_NAME_PLACEHOLDER/CODE_LOCATION_NAME_PLACEHOLDER_tests/__init__.py
dg_cli/templates/COMPONENT_TYPE/COMPONENT_TYPE_NAME_PLACEHOLDER.py.jinja
dg_cli/templates/DEPLOYMENT_NAME_PLACEHOLDER/dagster_cloud.yaml.jinja
dg_cli/templates/DEPLOYMENT_NAME_PLACEHOLDER/.github/workflows/dagster-cloud-deploy.yaml.jinja
dg_cli/templates/DEPLOYMENT_NAME_PLACEHOLDER/code_locations/.gitkeep
dagster_dg-1.0.3.dist-info/LICENSE
dagster_dg-1.0.3.dist-info/METADATA
dagster_dg-1.0.3.dist-info/WHEEL
dagster_dg-1.0.3.dist-info/entry_points.txt
dagster_dg-1.0.3.dist-info/top_level.txt
dagster_dg-1.0.3.dist-info/RECORD
