Metadata-Version: 2.1
Name: dagster-dg
Version: 1.0.3
Home-page: https://github.com/dagster-io/dagster/tree/master/python_modules/libraries/dg-cli
Author: Dagster Labs
Author-email: hello@dagsterlabs.com
License: Apache-2.0
Classifier: Programming Language :: Python :: 3.9
Classifier: Programming Language :: Python :: 3.10
Classifier: Programming Language :: Python :: 3.11
Classifier: Programming Language :: Python :: 3.12
Classifier: License :: OSI Approved :: Apache Software License
Classifier: Operating System :: OS Independent
License-File: LICENSE
Requires-Dist: Jinja2
Requires-Dist: tomli
Requires-Dist: click>=8
Requires-Dist: typing_extensions<5,>=4.4.0
Provides-Extra: test
Requires-Dist: pytest; extra == "test"
